{
  "expo": {
    "name": "معامل اركان للتحاليل",
    "slug": "arkanlabslug",
    "scheme": "arkanlabscheme",
    "version": "3.0",
    "icon": "./AppIcons/arkanlab/arkanlab1024.png",
    "orientation": "portrait",
    "notification": {
      "icon": "./AppIcons/arkanlab/arkanlab1024.png"
    },
    "splash": {
      "image": "./AppIcons/arkanlab/arkanlab1024.png",
      "backgroundColor": "#ffffff",
      "resizeMode": "contain"
    },
    "assetBundlePatterns": [
      "**/*"
    ],
    "ios": {
      "bundleIdentifier": "com.tabex.series.arkan",
      "buildNumber": "3",
      "supportsTablet": true,
      "infoPlist": {
        "NSUserTrackingUsageDescription": "This identifier email will be used to deliver personalized ads to you."
      }
    },
    "android": {
      "softwareKeyboardLayoutMode": "pan",
      "googleServicesFile": "./GoogleServicesJSONFiles/arkanlab-google-services.json",
      "package": "com.tabex.series.arkanlab",
      "icon": "./AppIcons/arkanlab/arkanlab512.png",
      "versionCode": 3,
      "permissions": [
        "INTERNET",
        "MODIFY_AUDIO_SETTINGS",
        "READ_EXTERNAL_STORAGE",
        "SYSTEM_ALERT_WINDOW",
        "VIBRATE",
        "WRITE_EXTERNAL_STORAGE"
      ],
      "adaptiveIcon": {
        "foregroundImage": "./AppIcons/arkanlab/arkanlab512.png",
        "backgroundColor": "#ffffff"
      }
    },
    "description": "",
    "extra": {
      "instapikey": "64e523a50a386",
      "projectsrctype": "subdomain",
      "hastrackingpermissions": "yes",
      "iossdk": "48",
      "androidsdk": "48",
      "eas": {
        "projectId": "f87708a0-43f0-47f7-8ac5-175f15172322"
      }
    },
    "plugins": [
      [
        "expo-tracking-transparency",
        {
          "userTrackingPermission": "This identifier email will be used to deliver personalized ads to you."
        }
      ]
    ],
    "runtimeVersion": {
      "policy": "sdkVersion"
    },
    "updates": {
      "url": "https://u.expo.dev/f87708a0-43f0-47f7-8ac5-175f15172322"
    }
  }
}
