{
  "expo": {
    "name": "MOD EG",
    "slug": "modslug",
    "scheme": "modscheme",
    "version": "2.0",
    "icon": "./AppIcons/mod/mod1024.png",
    "notification": {
      "icon": "./AppIcons/mod/mod1024.png"
    },
    "splash": {
      "image": "./AppIcons/mod/mod1024.png",
      "backgroundColor": "#000000",
      "resizeMode": "contain"
    },
    "assetBundlePatterns": [
      "**/*"
    ],
    "ios": {
      "bundleIdentifier": "com.tabex.series.mod",
      "buildNumber": "2",
      "supportsTablet": true,
      "infoPlist": {
        "NSUserTrackingUsageDescription": "This identifier email will be used to deliver personalized ads to you."
      }
    },
    "android": {
      "softwareKeyboardLayoutMode": "pan",
      "googleServicesFile": "./GoogleServicesJSONFiles/mod-google-services.json",
      "package": "com.tabex.series.mod",
      "icon": "./AppIcons/mod/mod512.png",
      "versionCode": 2,
      "permissions": [
        "INTERNET",
        "MODIFY_AUDIO_SETTINGS",
        "READ_EXTERNAL_STORAGE",
        "SYSTEM_ALERT_WINDOW",
        "VIBRATE",
        "WRITE_EXTERNAL_STORAGE"
      ],
      "adaptiveIcon": {
        "foregroundImage": "./AppIcons/mod/mod512.png",
        "backgroundColor": "#000000"
      }
    },
    "description": "",
    "extra": {
      "instapikey": "640f377472c7f",
      "projectsrctype": "subdomain",
      "hastrackingpermissions": "yes",
      "iossdk": "48",
      "androidsdk": "48",
      "eas": {
        "projectId": "06f0da04-7411-4526-8920-006993fe61eb"
      }
    },
    "plugins": [
      [
        "expo-tracking-transparency",
        {
          "userTrackingPermission": "This identifier email will be used to deliver personalized ads to you."
        }
      ]
    ]
  }
}
