{
  "expo": {
    "name": "UNO - اونو",
    "slug": "unoslug",
    "scheme": "unoscheme",
    "version": "1.0",
    "icon": "./AppIcons/uno/uno1024.png",
    "orientation": "portrait",
    "notification": {
      "icon": "./AppIcons/uno/uno1024.png"
    },
    "splash": {
      "image": "./AppIcons/uno/uno1024.png",
      "backgroundColor": "#ffffff",
      "resizeMode": "contain"
    },
    "assetBundlePatterns": [
      "**/*"
    ],
    "ios": {
      "bundleIdentifier": "com.tabex.series.uno",
      "buildNumber": "1",
      "supportsTablet": true,
      "infoPlist": {
        "NSUserTrackingUsageDescription": "This identifier email will be used to deliver personalized ads to you."
      }
    },
    "android": {
      "softwareKeyboardLayoutMode": "pan",
      "googleServicesFile": "./GoogleServicesJSONFiles/uno-google-services.json",
      "package": "com.tabex.series.uno",
      "icon": "./AppIcons/uno/uno512.png",
      "versionCode": 1,
      "permissions": [
        "INTERNET",
        "MODIFY_AUDIO_SETTINGS",
        "READ_EXTERNAL_STORAGE",
        "SYSTEM_ALERT_WINDOW",
        "VIBRATE",
        "WRITE_EXTERNAL_STORAGE"
      ],
      "adaptiveIcon": {
        "foregroundImage": "./AppIcons/uno/uno512.png",
        "backgroundColor": "#ffffff"
      }
    },
    "description": "",
    "extra": {
      "instapikey": "64f82e70687e3",
      "projectsrctype": "subdomain",
      "hastrackingpermissions": "yes",
      "iossdk": "48",
      "androidsdk": "48",
      "expoaccountwhoami": "tabexdevinfo@gmail.com",
      "eas": {
        "projectId": "5574a437-33ff-4c28-9bb6-b18e18b912c3"
      }
    },
    "plugins": [
      [
        "expo-tracking-transparency",
        {
          "userTrackingPermission": "This identifier email will be used to deliver personalized ads to you."
        }
      ]
    ],
    "runtimeVersion": {
      "policy": "sdkVersion"
    },
    "updates": {
      "url": "https://u.expo.dev/5574a437-33ff-4c28-9bb6-b18e18b912c3"
    }
  }
}
